kylix/__init__.py
kylix/example.py
kylix-0.1.0.dist-info/METADATA
kylix-0.1.0.dist-info/WHEEL
kylix-0.1.0.dist-info/licenses/LICENSE
kylix-0.1.0.dist-info/RECORD
