Metadata-Version: 2.1
Name: kylix
Version: 0.1.0
Summary: kylix CLI package
Author-email: "swarmbits.com" <distribution@swarmbits.com>
License-File: LICENSE
Classifier: License :: OSI Approved :: MIT License
Classifier: Operating System :: OS Independent
Classifier: Programming Language :: Python :: 3
Requires-Python: >=3.7
